{
  "date": "2026-06-29",
  "districts": [
    {
      "name": "Ballia",
      "hindi": "बलिया",
      "rates": {},
      "weather": {
        "tmax": 36,
        "tmin": 26,
        "rain_prob": 75,
        "rain_mm": 8.7,
        "warnings": [
          "⚠️ तेज़ बारिश की संभावना — कटी फसल/अनाज ढककर रखें, मंडी ले जाने से पहले मौसम देख लें।"
        ]
      },
      "message": "🌾 *अग्रोमंच दैनिक भाव*\n📅 29 जून 2026, सोमवार\n📍 ज़िला: बलिया\n\nआज मंडी भाव उपलब्ध नहीं है।\n\n*मौसम:* 36°/26°C, बारिश की संभावना 75%\n⚠️ तेज़ बारिश की संभावना — कटी फसल/अनाज ढककर रखें, मंडी ले जाने से पहले मौसम देख लें।\n\nℹ️ भाव मंडी के हिसाब से थोड़ा ऊपर-नीचे हो सकता है।\n📲 रोज़ का भाव सीधे फ़ोन पर — Agromanch app:\nhttps://play.google.com/store/apps/details?id=com.agromanch.app"
    },
    {
      "name": "Mau",
      "hindi": "मऊ",
      "rates": {},
      "weather": {
        "tmax": 36,
        "tmin": 26,
        "rain_prob": 61,
        "rain_mm": 10.1,
        "warnings": []
      },
      "message": "🌾 *अग्रोमंच दैनिक भाव*\n📅 29 जून 2026, सोमवार\n📍 ज़िला: मऊ\n\nआज मंडी भाव उपलब्ध नहीं है।\n\n*मौसम:* 36°/26°C, बारिश की संभावना 61%\n\nℹ️ भाव मंडी के हिसाब से थोड़ा ऊपर-नीचे हो सकता है।\n📲 रोज़ का भाव सीधे फ़ोन पर — Agromanch app:\nhttps://play.google.com/store/apps/details?id=com.agromanch.app"
    },
    {
      "name": "Deoria",
      "hindi": "देवरिया",
      "rates": {},
      "weather": {
        "tmax": 36,
        "tmin": 27,
        "rain_prob": 61,
        "rain_mm": 14.4,
        "warnings": []
      },
      "message": "🌾 *अग्रोमंच दैनिक भाव*\n📅 29 जून 2026, सोमवार\n📍 ज़िला: देवरिया\n\nआज मंडी भाव उपलब्ध नहीं है।\n\n*मौसम:* 36°/27°C, बारिश की संभावना 61%\n\nℹ️ भाव मंडी के हिसाब से थोड़ा ऊपर-नीचे हो सकता है।\n📲 रोज़ का भाव सीधे फ़ोन पर — Agromanch app:\nhttps://play.google.com/store/apps/details?id=com.agromanch.app"
    },
    {
      "name": "Ghazipur",
      "hindi": "ग़ाज़ीपुर",
      "rates": {},
      "weather": {
        "tmax": 38,
        "tmin": 27,
        "rain_prob": 67,
        "rain_mm": 7.6,
        "warnings": []
      },
      "message": "🌾 *अग्रोमंच दैनिक भाव*\n📅 29 जून 2026, सोमवार\n📍 ज़िला: ग़ाज़ीपुर\n\nआज मंडी भाव उपलब्ध नहीं है।\n\n*मौसम:* 38°/27°C, बारिश की संभावना 67%\n\nℹ️ भाव मंडी के हिसाब से थोड़ा ऊपर-नीचे हो सकता है।\n📲 रोज़ का भाव सीधे फ़ोन पर — Agromanch app:\nhttps://play.google.com/store/apps/details?id=com.agromanch.app"
    },
    {
      "name": "Azamgarh",
      "hindi": "आज़मगढ़",
      "rates": {},
      "weather": {
        "tmax": 36,
        "tmin": 26,
        "rain_prob": 63,
        "rain_mm": 8.1,
        "warnings": []
      },
      "message": "🌾 *अग्रोमंच दैनिक भाव*\n📅 29 जून 2026, सोमवार\n📍 ज़िला: आज़मगढ़\n\nआज मंडी भाव उपलब्ध नहीं है।\n\n*मौसम:* 36°/26°C, बारिश की संभावना 63%\n\nℹ️ भाव मंडी के हिसाब से थोड़ा ऊपर-नीचे हो सकता है।\n📲 रोज़ का भाव सीधे फ़ोन पर — Agromanch app:\nhttps://play.google.com/store/apps/details?id=com.agromanch.app"
    }
  ]
}